AUTHORS.rst
CONTRIBUTING.rst
HISTORY.rst
LICENSE
MANIFEST.in
README.rst
setup.cfg
setup.py
bin/messier
docs/Makefile
docs/authors.rst
docs/conf.py
docs/contributing.rst
docs/history.rst
docs/index.rst
docs/installation.rst
docs/make.bat
docs/readme.rst
docs/usage.rst
messier/__init__.py
messier/ansible_handler.py
messier/exceptions.py
messier/messier.py
messier/serverspec_handler.py
messier/vagrant_handler.py
messier.egg-info/PKG-INFO
messier.egg-info/SOURCES.txt
messier.egg-info/dependency_links.txt
messier.egg-info/not-zip-safe
messier.egg-info/pbr.json
messier.egg-info/requires.txt
messier.egg-info/top_level.txt
tests/__init__.py
tests/test_messier.py