Metadata-Version: 1.1
Name: messier
Version: 0.1.0
Summary: Test Ansible roles with Vagrant, similar to Test Kitchen
Home-page: https://github.com/conorsch/messier
Author: Conor Schaefer
Author-email: conor.schaefer@gmail.com
License: GPLv3
Keywords: messier
Platform: UNKNOWN
Classifier: Development Status :: 2 - Pre-Alpha
Classifier: Intended Audience :: Developers
Classifier: Natural Language :: English
Classifier: Programming Language :: Python :: 2
Classifier: Programming Language :: Python :: 2.6
Classifier: Programming Language :: Python :: 2.7
Classifier: Programming Language :: Python :: 3
Classifier: Programming Language :: Python :: 3.3
Classifier: Programming Language :: Python :: 3.4
Classifier: Programming Language :: Python :: 3.5
